huffman/__init__.py
huffman/schedule_runner.py
huffman/src/__init__.py
huffman/src/file_persistence.py
huffman/src/huffman_tree.py
huffman/src/schedule_exceptions.py
huffman/src/schedule_parser.py
huffman/src/scheduler.py
huffman/src/timed_item.py
huffman/src/timed_schedule_config.py
huffman/src/tree.py
huffman_tree_scheduler-0.0.1.dist-info/LICENSE
huffman_tree_scheduler-0.0.1.dist-info/METADATA
huffman_tree_scheduler-0.0.1.dist-info/WHEEL
huffman_tree_scheduler-0.0.1.dist-info/top_level.txt
huffman_tree_scheduler-0.0.1.dist-info/RECORD
