Metadata-Version: 2.1
Name: huffman-tree-scheduler
Version: 0.0.1
Summary: a -to do- tree
Home-page: UNKNOWN
Author: grebob
Author-email: bobbe.cooper@gmail.com
License: UNKNOWN
Platform: UNKNOWN
Classifier: Programming Language :: Python :: 3.9
Classifier: License :: OSI Approved :: MIT License
Classifier: Operating System :: OS Independent
Requires-Python: >=3.6
